jolla
