Metadata-Version: 1.1
Name: jolla
Version: 1.1.11
Summary: high performance RESTful framework
Home-page: https://github.com/salamer/jolla
Author: aljun
Author-email: salamer_gaga@163.com
License: Apache
Download-URL: https://github.com/salamer/jolla
Keywords: back-end,framework,RESTful,gevent
Platform: UNKNOWN
Classifier: Development Status :: 3 - Alpha
Classifier: License :: OSI Approved :: Apache Software License
Classifier: Environment :: Web Environment
Classifier: Programming Language :: Python :: 2.7
Classifier: Topic :: Internet :: WWW/HTTP
Classifier: Topic :: Software Development :: Libraries :: Python Modules
